geocode_pagenames
