Metadata-Version: 1.0
Name: localwiki-geocode-pagenames
Version: 0.1.1
Summary: A script to semi-automatically map pages in a LocalWiki instance
Home-page: https://github.com/philipn/localwiki_geocode_pagenames
Author: Philip Neustrom
Author-email: philipn@gmail.com
License: UNKNOWN
Platform: UNKNOWN
